Workbook

Sheet RAW SCORECARD
A1: customer_id | B1: age | C1: employment_type | D1: monthly_income | E1: income_stability_score | F1: rent_amount | G1: location_type | H1: avg_inflow | I1: avg_outflow | J1: avg_net_cashflow | K1: avg_expense_ratio | L1: avg_balance | M1: inflow_volatility | N1: rent_to_income_ratio | O1: loan_amount | P1: repayment_status | Q1: days_past_due | R1: default_flag | S1: net_cashflow_ratio | T1: financial_pressure | U1: stability_score | V1: liquidity_strength | W1: risk_score | X1: risk_category | Y1: Column1
A2: CUS00001 | B2: 45 | C2: salary | D2: 142900 | E2: 0.826 | F2: 41000 | G2: urban | H2: 134070.17 | I2: 106236.62 | J2: 27833.553 | K2: 0.84878531 | L2: 312667.68 | M2: 34877.879 | N2: 0.28691393 | O2: 328000 | P2: paid_on_time | Q2: 0 | R2: 0 | S2: 0.56284576 | T2: 0.36270986 | U2: 0.70013149 | V2: 0.39063039 | W2: 59.878601 | X2: Medium Risk
A3: CUS00002 | B3: 24 | C3: mixed | D3: 164600 | E3: 0.483 | F3: 47000 | G3: urban | H3: 154352.11 | I3: 118846.68 | J3: 35505.432 | K3: 0.79143225 | L3: 332077.39 | M3: 25841.697 | N3: 0.2855407 | O3: 188000 | P3: late | Q3: 60 | R3: 0 | S3: 0.62463792 | T3: 0.31446401 | U3: 0.37412276 | V3: 0.34501179 | W3: 49.930181 | X3: Medium Risk
A4: CUS00003 | B4: 52 | C4: business | D4: 342300 | E4: 0.264 | F4: 116000 | G4: urban | H4: 262416.72 | I4: 207895.63 | J4: 54521.089 | K4: 0.80764018 | L4: 963975.17 | M4: 114604.76 | N4: 0.33888402 | O4: 348000 | P4: paid_on_time | Q4: 0 | R4: 0 | S4: 0.56328922 | T4: 0.4456802 | U4: 0.063979544 | V4: 0.55866193 | W4: 38.491455 | X4: High Risk
A5: CUS00004 | B5: 45 | C5: business | D5: 188100 | E5: 0.259 | F5: 59000 | G5: urban | H5: 163357.3 | I5: 134737.3 | J5: 28619.999 | K5: 0.84692901 | L5: 593602.23 | M5: 68252.193 | N5: 0.31366295 | O5: 354000 | P5: default | Q5: 180 | R5: 1 | S5: 0.47354984 | T5: 0.42355121 | U5: 0.062530321 | V5: 0.64950779 | W5: 39.575428 | X5: High Risk
A6: CUS00005 | B6: 31 | C6: salary | D6: 134300 | E6: 0.774 | F6: 30000 | G6: urban | H6: 139781.12 | I6: 95539.464 | J6: 44241.661 | K6: 0.69702129 | L6: 396309.5 | M6: 21427.873 | N6: 0.22338049 | O6: 210000 | P6: paid_on_time | Q6: 0 | R6: 0 | S6: 0.86293392 | T6: 0.12116055 | U6: 0.72122382 | V6: 0.59470941 | W6: 76.446214 | X6: Low Risk
A7: CUS00006 | B7: 27 | C7: salary | D7: 201700 | E7: 0.792 | F7: 49000 | G7: urban | H7: 200639.14 | I7: 138606.92 | J7: 62032.23 | K7: 0.72472611 | L7: 789818.44 | M7: 38991.643 | N7: 0.24293505 | O7: 539000 | P7: paid_on_time | Q7: 0 | R7: 0 | S7: 0.84272574 | T7: 0.17715727 | U7: 0.71044789 | V7: 0.8528159 | W7: 79.248162 | X7: Low Risk
A8: CUS00007 | B8: 33 | C8: salary | D8: 233900 | E8: 0.884 | F8: 54000 | G8: semi-urban | H8: 240312.62 | I8: 175052.57 | J8: 65260.052 | K8: 0.74577566 | L8: 549904.65 | M8: 33657.416 | N8: 0.23086789 | O8: 270000 | P8: default | Q8: 120 | R8: 1 | S8: 0.73908877 | T8: 0.16647048 | U8: 0.86185104 | V8: 0.43423497 | W8: 74.941703 | X8: Low Risk
A9: CUS00008 | B9: 33 | C9: mixed | D9: 124300 | E9: 0.687 | F9: 30000 | G9: rural | H9: 106214.28 | I9: 93532.445 | J9: 12681.836 | K9: 0.92989596 | L9: 353201.48 | M9: 23913.773 | N9: 0.24135157 | O9: 270000 | P9: late | Q9: 60 | R9: 0 | S9: 0.31978843 | T9: 0.31018932 | U9: 0.57238273 | V9: 0.56544411 | W9: 56.833424 | X9: Medium Risk
A10: CUS00009 | B10: 48 | C10: business | D10: 313100 | E10: 0.32 | F10: 75000 | G10: urban | H10: 297231.87 | I10: 219144.25 | J10: 78087.619 | K10: 0.73345078 | L10: 716645.72 | M10: 118834.17 | N10: 0.23954008 | O10: 225000 | P10: default | Q10: 180 | R10: 1 | S10: 0.7147103 | T10: 0.17613826 | U10: 0.12446598 | V10: 0.41760901 | W10: 48.144996 | X10: Medium Risk
A11: CUS00010 | B11: 42 | C11: business | D11: 352000 | E11: 0.218 | F11: 80000 | G11: urban | H11: 386345.11 | I11: 321245.34 | J11: 65099.77 | K11: 0.80968988 | L11: 958553.48 | M11: 135163.79 | N11: 0.22727273 | O11: 480000 | P11: paid_on_time | Q11: 0 | R11: 0 | S11: 0.45509529 | T11: 0.19904685 | U11: 0.033971881 | V11: 0.53378241 | W11: 42.719688 | X11: Medium Risk
A12: CUS00011 | B12: 30 | C12: salary | D12: 218900 | E12: 0.892 | F12: 52000 | G12: rural | H12: 200497.39 | I12: 147941.6 | J12: 52555.797 | K12: 0.76750209 | L12: 775005.71 | M12: 37094.637 | N12: 0.23755139 | O12: 208000 | P12: paid_on_time | Q12: 0 | R12: 0 | S12: 0.71308701 | T12: 0.19437348 | U12: 0.83128517 | V12: 0.75240881 | W12: 79.008258 | X12: Low Risk
A13: CUS00012 | B13: 23 | C13: mixed | D13: 193400 | E13: 0.741 | F13: 67000 | G13: urban | H13: 180263.27 | I13: 147479.8 | J13: 32783.477 | K13: 0.83793865 | L13: 498380.94 | M13: 39110.163 | N13: 0.34643226 | O13: 469000 | P13: paid_on_time | Q13: 0 | R13: 0 | S13: 0.49191751 | T13: 0.49131449 | U13: 0.63730804 | V13: 0.49466858 | W13: 54.838481 | X13: Medium Risk
... A2001: CUS02000 | B2001: 36 | C2001: salary | D2001: 180200 | E2001: 0.92 | F2001: 62000 | G2001: semi-urban | H2001: 162877.25 | I2001: 136662.49 | J2001: 26214.757 | K2001: 0.8729642 | L2001: 345697.97 | M2001: 30237.06 | N2001: 0.34406215 | O2001: 310000 | P2001: paid_on_time | Q2001: 0 | R2001: 0 | S2001: 0.43428061 | T2001: 0.51899588 | U2001: 0.86259294 | V2001: 0.31851091 | W2001: 57.505304 | X2001: Medium Risk

Sheet MACHINE LEARNING OUTPUT 
A1: customer_id | B1: age | C1: employment_type | D1: monthly_income | E1: income_stability_score | F1: rent_amount | G1: location_type | H1: avg_inflow | I1: avg_outflow | J1: avg_net_cashflow | K1: avg_expense_ratio | L1: avg_balance | M1: inflow_volatility | N1: rent_to_income_ratio | O1: loan_amount | P1: repayment_status | Q1: days_past_due | R1: default_flag | S1: net_cashflow_ratio | T1: financial_pressure | U1: stability_score | V1: liquidity_strength | W1: ml_pred | X1: ml_prob
A2: CUS00001 | B2: 45 | C2: salary | D2: 142900 | E2: 0.826 | F2: 41000 | G2: urban | H2: 134070.17 | I2: 106236.62 | J2: 27833.553 | K2: 0.84878531 | L2: 312667.68 | M2: 34877.879 | N2: 0.28691393 | O2: 328000 | P2: paid_on_time | Q2: 0 | R2: 0 | S2: 0.20760437 | T2: 0.24352832 | U2: 0.65547936 | V2: 2.1880174 | W2: 0 | X2: 0.46842556
A3: CUS00002 | B3: 24 | C3: mixed | D3: 164600 | E3: 0.483 | F3: 47000 | G3: urban | H3: 154352.11 | I3: 118846.68 | J3: 35505.432 | K3: 0.79143225 | L3: 332077.39 | M3: 25841.697 | N3: 0.2855407 | O3: 188000 | P3: late | Q3: 60 | R3: 0 | S3: 0.23002881 | T3: 0.22598612 | U3: 0.41373269 | V3: 2.0174811 | W3: 1 | X3: 0.5790766
A4: CUS00003 | B4: 52 | C4: business | D4: 342300 | E4: 0.264 | F4: 116000 | G4: urban | H4: 262416.72 | I4: 207895.63 | J4: 54521.089 | K4: 0.80764018 | L4: 963975.17 | M4: 114604.76 | N4: 0.33888402 | O4: 348000 | P4: paid_on_time | Q4: 0 | R4: 0 | S4: 0.2077653 | T4: 0.27369635 | U4: 0.18375084 | V4: 2.8161705 | W4: 1 | X4: 0.67087302
A5: CUS00004 | B5: 45 | C5: business | D5: 188100 | E5: 0.259 | F5: 59000 | G5: urban | H5: 163357.3 | I5: 134737.3 | J5: 28619.999 | K5: 0.84692901 | L5: 593602.23 | M5: 68252.193 | N5: 0.31366295 | O5: 354000 | P5: default | Q5: 180 | R5: 1 | S5: 0.17519878 | T5: 0.26565025 | U5: 0.18267619 | V5: 3.1557801 | W5: 1 | X5: 0.66561917
A6: CUS00005 | B6: 31 | C6: salary | D6: 134300 | E6: 0.774 | F6: 30000 | G6: urban | H6: 139781.12 | I6: 95539.464 | J6: 44241.661 | K6: 0.69702129 | L6: 396309.5 | M6: 21427.873 | N6: 0.22338049 | O6: 210000 | P6: paid_on_time | Q6: 0 | R6: 0 | S6: 0.31650669 | T6: 0.15570096 | U6: 0.67112005 | V6: 2.950927 | W6: 0 | X6: 0.37718102
A7: CUS00006 | B7: 27 | C7: salary | D7: 201700 | E7: 0.792 | F7: 49000 | G7: urban | H7: 200639.14 | I7: 138606.92 | J7: 62032.23 | K7: 0.72472611 | L7: 789818.44 | M7: 38991.643 | N7: 0.24293505 | O7: 539000 | P7: paid_on_time | Q7: 0 | R7: 0 | S7: 0.30917312 | T7: 0.17606137 | U7: 0.66312933 | V7: 3.9158078 | W7: 0 | X7: 0.35239446
A8: CUS00007 | B8: 33 | C8: salary | D8: 233900 | E8: 0.884 | F8: 54000 | G8: semi-urban | H8: 240312.62 | I8: 175052.57 | J8: 65260.052 | K8: 0.74577566 | L8: 549904.65 | M8: 33657.416 | N8: 0.23086789 | O8: 270000 | P8: default | Q8: 120 | R8: 1 | S8: 0.27156315 | T8: 0.17217565 | U8: 0.77539997 | V8: 2.3510246 | W8: 0 | X8: 0.36911975
A9: CUS00008 | B9: 33 | C9: mixed | D9: 124300 | E9: 0.687 | F9: 30000 | G9: rural | H9: 106214.28 | I9: 93532.445 | J9: 12681.836 | K9: 0.92989596 | L9: 353201.48 | M9: 23913.773 | N9: 0.24135157 | O9: 270000 | P9: late | Q9: 60 | R9: 0 | S9: 0.11939859 | T9: 0.22443185 | U9: 0.56074927 | V9: 2.8415244 | W9: 1 | X9: 0.50772662
A10: CUS00009 | B10: 48 | C10: business | D10: 313100 | E10: 0.32 | F10: 75000 | G10: urban | H10: 297231.87 | I10: 219144.25 | J10: 78087.619 | K10: 0.73345078 | L10: 716645.72 | M10: 118834.17 | N10: 0.23954008 | O10: 225000 | P10: default | Q10: 180 | R10: 1 | S10: 0.26271618 | T10: 0.17569086 | U10: 0.22860361 | V10: 2.2888717 | W10: 1 | X10: 0.6310887
A11: CUS00010 | B11: 42 | C11: business | D11: 352000 | E11: 0.218 | F11: 80000 | G11: urban | H11: 386345.11 | I11: 321245.34 | J11: 65099.77 | K11: 0.80968988 | L11: 958553.48 | M11: 135163.79 | N11: 0.22727273 | O11: 480000 | P11: paid_on_time | Q11: 0 | R11: 0 | S11: 0.1685016 | T11: 0.18402043 | U11: 0.16149913 | V11: 2.7231633 | W11: 1 | X11: 0.67125919
A12: CUS00011 | B12: 30 | C12: salary | D12: 218900 | E12: 0.892 | F12: 52000 | G12: rural | H12: 200497.39 | I12: 147941.6 | J12: 52555.797 | K12: 0.76750209 | L12: 775005.71 | M12: 37094.637 | N12: 0.23755139 | O12: 208000 | P12: paid_on_time | Q12: 0 | R12: 0 | S12: 0.26212708 | T12: 0.18232119 | U12: 0.75273432 | V12: 3.5404555 | W12: 0 | X12: 0.34081527
A13: CUS00012 | B13: 23 | C13: mixed | D13: 193400 | E13: 0.741 | F13: 67000 | G13: urban | H13: 180263.27 | I13: 147479.8 | J13: 32783.477 | K13: 0.83793865 | L13: 498380.94 | M13: 39110.163 | N13: 0.34643226 | O13: 469000 | P13: paid_on_time | Q13: 0 | R13: 0 | S13: 0.18186443 | T13: 0.29028898 | U13: 0.60889362 | V13: 2.5769439 | W13: 0 | X13: 0.49576141
... A2001: CUS02000 | B2001: 36 | C2001: salary | D2001: 180200 | E2001: 0.92 | F2001: 62000 | G2001: semi-urban | H2001: 162877.25 | I2001: 136662.49 | J2001: 26214.757 | K2001: 0.8729642 | L2001: 345697.97 | M2001: 30237.06 | N2001: 0.34406215 | O2001: 310000 | P2001: paid_on_time | Q2001: 0 | R2001: 0 | S2001: 0.16094793 | T2001: 0.30035394 | U2001: 0.77595011 | V2001: 1.9184127 | W2001: 0 | X2001: 0.45084284

Sheet CREDIT RISK SCORECARD
A1: customer_id | B1: income_stability_score | C1: financial_pressure | D1: liquidity_strength | E1: net_cashflow_ratio | F1: weighted_score | G1: risk_score | H1: risk_category | I1: ML_PRED | J1: ML_PROB | K1: employment_type
A2: CUS00001 | B2: 0.826 | C2: 0.36270986 | D2: 0.39063039 | E2: 0.56284576 | F2: =(B2*0.35) + ((1-C2)*0.3) + (D2*0.2) + (E2*0.15) -> 0.64283998 | G2: =F2*100 -> 64.283998 | H2: =IF(G2<40," High Risk", IF(G2<70," Medium Risk", " Low Risk")) -> Medium Risk | I2: =VLOOKUP(A2, 'MACHINE LEARNING OUTPUT '!A:W, 23, FALSE) -> 0 | J2: =VLOOKUP(A2, 'MACHINE LEARNING OUTPUT '!A:X,24, FALSE) -> 0.46842556 | K2: =VLOOKUP(A2, 'MACHINE LEARNING OUTPUT '!A:C,3, FALSE) -> salary
A3: CUS00002 | B3: 0.483 | C3: 0.31446401 | D3: 0.39063039 | E3: 0.62463792 | F3: =(B3*0.35) + ((1-C3)*0.3) + (D3*0.2) + (E3*0.15) -> 0.54653256 | G3: =F3*100 -> 54.653256 | H3: =IF(G3<40," High Risk", IF(G3<70," Medium Risk", " Low Risk")) -> Medium Risk | I3: =VLOOKUP(A3, 'MACHINE LEARNING OUTPUT '!A:W, 23, FALSE) -> 1 | J3: =VLOOKUP(A3, 'MACHINE LEARNING OUTPUT '!A:X,24, FALSE) -> 0.5790766 | K3: =VLOOKUP(A3, 'MACHINE LEARNING OUTPUT '!A:C,3, FALSE) -> mixed
A4: CUS00003 | B4: 0.264 | C4: 0.31446401 | D4: 0.55866193 | E4: 0.56328922 | F4: =(B4*0.35) + ((1-C4)*0.3) + (D4*0.2) + (E4*0.15) -> 0.49428657 | G4: =F4*100 -> 49.428657 | H4: =IF(G4<40," High Risk", IF(G4<70," Medium Risk", " Low Risk")) -> Medium Risk | I4: =VLOOKUP(A4, 'MACHINE LEARNING OUTPUT '!A:W, 23, FALSE) -> 1 | J4: =VLOOKUP(A4, 'MACHINE LEARNING OUTPUT '!A:X,24, FALSE) -> 0.67087302 | K4: =VLOOKUP(A4, 'MACHINE LEARNING OUTPUT '!A:C,3, FALSE) -> business
A5: CUS00004 | B5: 0.259 | C5: 0.42355121 | D5: 0.64950779 | E5: 0.47354984 | F5: =(B5*0.35) + ((1-C5)*0.3) + (D5*0.2) + (E5*0.15) -> 0.46451867 | G5: =F5*100 -> 46.451867 | H5: =IF(G5<40," High Risk", IF(G5<70," Medium Risk", " Low Risk")) -> Medium Risk | I5: =VLOOKUP(A5, 'MACHINE LEARNING OUTPUT '!A:W, 23, FALSE) -> 1 | J5: =VLOOKUP(A5, 'MACHINE LEARNING OUTPUT '!A:X,24, FALSE) -> 0.66561917 | K5: =VLOOKUP(A5, 'MACHINE LEARNING OUTPUT '!A:C,3, FALSE) -> business
A6: CUS00005 | B6: 0.774 | C6: 0.12116055 | D6: 0.59470941 | E6: 0.86293392 | F6: =(B6*0.35) + ((1-C6)*0.3) + (D6*0.2) + (E6*0.15) -> 0.7829338 | G6: =F6*100 -> 78.29338 | H6: =IF(G6<40," High Risk", IF(G6<70," Medium Risk", " Low Risk")) -> Low Risk | I6: =VLOOKUP(A6, 'MACHINE LEARNING OUTPUT '!A:W, 23, FALSE) -> 0 | J6: =VLOOKUP(A6, 'MACHINE LEARNING OUTPUT '!A:X,24, FALSE) -> 0.37718102 | K6: =VLOOKUP(A6, 'MACHINE LEARNING OUTPUT '!A:C,3, FALSE) -> salary
A7: CUS00006 | B7: 0.792 | C7: 0.17715727 | D7: 0.8528159 | E7: 0.84272574 | F7: =(B7*0.35) + ((1-C7)*0.3) + (D7*0.2) + (E7*0.15) -> 0.82102486 | G7: =F7*100 -> 82.102486 | H7: =IF(G7<40," High Risk", IF(G7<70," Medium Risk", " Low Risk")) -> Low Risk | I7: =VLOOKUP(A7, 'MACHINE LEARNING OUTPUT '!A:W, 23, FALSE) -> 0 | J7: =VLOOKUP(A7, 'MACHINE LEARNING OUTPUT '!A:X,24, FALSE) -> 0.35239446 | K7: =VLOOKUP(A7, 'MACHINE LEARNING OUTPUT '!A:C,3, FALSE) -> salary
A8: CUS00007 | B8: 0.884 | C8: 0.16647048 | D8: 0.43423497 | E8: 0.73908877 | F8: =(B8*0.35) + ((1-C8)*0.3) + (D8*0.2) + (E8*0.15) -> 0.75716917 | G8: =F8*100 -> 75.716917 | H8: =IF(G8<40," High Risk", IF(G8<70," Medium Risk", " Low Risk")) -> Low Risk | I8: =VLOOKUP(A8, 'MACHINE LEARNING OUTPUT '!A:W, 23, FALSE) -> 0 | J8: =VLOOKUP(A8, 'MACHINE LEARNING OUTPUT '!A:X,24, FALSE) -> 0.36911975 | K8: =VLOOKUP(A8, 'MACHINE LEARNING OUTPUT '!A:C,3, FALSE) -> salary
A9: CUS00008 | B9: 0.687 | C9: 0.31018932 | D9: 0.56544411 | E9: 0.31978843 | F9: =(B9*0.35) + ((1-C9)*0.3) + (D9*0.2) + (E9*0.15) -> 0.60845029 | G9: =F9*100 -> 60.845029 | H9: =IF(G9<40," High Risk", IF(G9<70," Medium Risk", " Low Risk")) -> Medium Risk | I9: =VLOOKUP(A9, 'MACHINE LEARNING OUTPUT '!A:W, 23, FALSE) -> 1 | J9: =VLOOKUP(A9, 'MACHINE LEARNING OUTPUT '!A:X,24, FALSE) -> 0.50772662 | K9: =VLOOKUP(A9, 'MACHINE LEARNING OUTPUT '!A:C,3, FALSE) -> mixed
A10: CUS00009 | B10: 0.32 | C10: 0.17613826 | D10: 0.41760901 | E10: 0.7147103 | F10: =(B10*0.35) + ((1-C10)*0.3) + (D10*0.2) + (E10*0.15) -> 0.54988687 | G10: =F10*100 -> 54.988687 | H10: =IF(G10<40," High Risk", IF(G10<70," Medium Risk", " Low Risk")) -> Medium Risk | I10: =VLOOKUP(A10, 'MACHINE LEARNING OUTPUT '!A:W, 23, FALSE) -> 1 | J10: =VLOOKUP(A10, 'MACHINE LEARNING OUTPUT '!A:X,24, FALSE) -> 0.6310887 | K10: =VLOOKUP(A10, 'MACHINE LEARNING OUTPUT '!A:C,3, FALSE) -> business
A11: CUS00010 | B11: 0.218 | C11: 0.19904685 | D11: 0.53378241 | E11: 0.45509529 | F11: =(B11*0.35) + ((1-C11)*0.3) + (D11*0.2) + (E11*0.15) -> 0.49160672 | G11: =F11*100 -> 49.160672 | H11: =IF(G11<40," High Risk", IF(G11<70," Medium Risk", " Low Risk")) -> Medium Risk | I11: =VLOOKUP(A11, 'MACHINE LEARNING OUTPUT '!A:W, 23, FALSE) -> 1 | J11: =VLOOKUP(A11, 'MACHINE LEARNING OUTPUT '!A:X,24, FALSE) -> 0.67125919 | K11: =VLOOKUP(A11, 'MACHINE LEARNING OUTPUT '!A:C,3, FALSE) -> business
A12: CUS00011 | B12: 0.892 | C12: 0.19437348 | D12: 0.75240881 | E12: 0.71308701 | F12: =(B12*0.35) + ((1-C12)*0.3) + (D12*0.2) + (E12*0.15) -> 0.81133277 | G12: =F12*100 -> 81.133277 | H12: =IF(G12<40," High Risk", IF(G12<70," Medium Risk", " Low Risk")) -> Low Risk | I12: =VLOOKUP(A12, 'MACHINE LEARNING OUTPUT '!A:W, 23, FALSE) -> 0 | J12: =VLOOKUP(A12, 'MACHINE LEARNING OUTPUT '!A:X,24, FALSE) -> 0.34081527 | K12: =VLOOKUP(A12, 'MACHINE LEARNING OUTPUT '!A:C,3, FALSE) -> salary
A13: CUS00012 | B13: 0.741 | C13: 0.49131449 | D13: 0.49466858 | E13: 0.49191751 | F13: =(B13*0.35) + ((1-C13)*0.3) + (D13*0.2) + (E13*0.15) -> 0.584677 | G13: =F13*100 -> 58.4677 | H13: =IF(G13<40," High Risk", IF(G13<70," Medium Risk", " Low Risk")) -> Medium Risk | I13: =VLOOKUP(A13, 'MACHINE LEARNING OUTPUT '!A:W, 23, FALSE) -> 0 | J13: =VLOOKUP(A13, 'MACHINE LEARNING OUTPUT '!A:X,24, FALSE) -> 0.49576141 | K13: =VLOOKUP(A13, 'MACHINE LEARNING OUTPUT '!A:C,3, FALSE) -> mixed
... A2001: CUS02000 | B2001: 0.92 | C2001: 0.51899588 | D2001: 0.31851091 | E2001: 0.43428061 | F2001: =(B2001*0.35) + ((1-C2001)*0.3) + (D2001*0.2) + (E2001*0.15) -> 0.59514551 | G2001: =F2001*100 -> 59.514551 | H2001: =IF(G2001<40," High Risk", IF(G2001<70," Medium Risk", " Low Risk")) -> Medium Risk | I2001: =VLOOKUP(A2001, 'MACHINE LEARNING OUTPUT '!A:W, 23, FALSE) -> 0 | J2001: =VLOOKUP(A2001, 'MACHINE LEARNING OUTPUT '!A:X,24, FALSE) -> 0.45084284 | K2001: =VLOOKUP(A2001, 'MACHINE LEARNING OUTPUT '!A:C,3, FALSE) -> salary

Sheet ANALYSIS
A1: Total Borrowers | B1: 2000 | E1: Feature | F1: Impact | G1: Value
A2: High Risk % | B2: =COUNTIF('CREDIT RISK SCORECARD'!H:H," High Risk")/COUNTA('CREDIT RISK SCORECARD'!A:A) -> 0.026486757 | E2: financial_pressure | F2: Increases Risk | G2: 1.12
A3: Medium Risk % | B3: =COUNTIF('CREDIT RISK SCORECARD'!H:H," Medium Risk")/COUNTA('CREDIT RISK SCORECARD'!A:A) -> 0.55572214 | E3: stability_score | F3: Reduces Risk | G3: -1.91
A4: Low Risk % | B4: =COUNTIF('CREDIT RISK SCORECARD'!H:H," Low Risk")/COUNTA('CREDIT RISK SCORECARD'!A:A) -> 0.41729135 | E4: net_cashflow_ratio | F4: Reduces Risk | G4: -1.14
A5: Avg Default Probability | B5: =AVERAGE(ml_output__5[ml_prob]) -> 0.47964902 | E5: liquidity_strength | F5: Weak Effect | G5: -0.16
A7: Borrower Risk Distribution
A8: Row Labels | B8: Count of customer_id | F8: Average Default Risk by Segment
A9: Medium Risk | B9: 1112 | F9: Row Labels | G9: Average of ML_PROB
A10: Low Risk | B10: 835 | F10: Medium Risk | G10: 0.54748635
A11: High Risk | B11: 53 | F11: Low Risk | G11: 0.3745052
A12: Grand Total | B12: 2000 | F12: High Risk | G12: 0.71285627
F13: Grand Total | G13: 0.47964902
A14: Scorecard vs Machine Learning Alignment
A15: Count of customer_id | B15: Column Labels | F15: Average Default Risk by Employment type
A16: Row Labels | B16: 0 | C16: 1 | D16: Grand Total | F16: Row Labels | G16: Average of ML_PROB
A17: Medium Risk | B17: 370 | C17: 742 | D17: 1112 | F17: business | G17: 0.61913712
A18: Low Risk | B18: 828 | C18: 7 | D18: 835 | F18: mixed | G18: 0.49595831
A19: High Risk | C19: 53 | D19: 53 | F19: salary | G19: 0.38678136
A20: Grand Total | B20: 1198 | C20: 802 | D20: 2000 | F20: Grand Total | G20: 0.47964902
A24: Default Probability distribution

Sheet DASHBOARD

Sheet APPLICATION VIEW
A7: CUSTOMER ID | B7: EMPLOYMENT TYPE | C7: INCOME | D7: RENT | E7: RISK CATEGORY | F7: ML PREDICTION | G7: ML PROBABILITY | H7: DECISION | I7: INDICATOR
A8: CUS00001 | B8: salary | C8: 142900 | D8: 41000 | E8: =VLOOKUP(A8,'CREDIT RISK SCORECARD'!A:H,8, FALSE) -> Medium Risk | F8: Safe | G8: 0.46842556 | H8: =IF(E:E=" Low Risk","APPROVE", IF(E:E=" Medium Risk","REVIEW","REJECT")) -> REVIEW | I8: =IF(Table9[[#This Row],[DECISION]]="Approve",3,IF(Table9[[#This Row],[DECISION]]="Review",2,1)) -> 2
A9: CUS00002 | B9: mixed | C9: 164600 | D9: 47000 | E9: =VLOOKUP(A9,'CREDIT RISK SCORECARD'!A:H,8, FALSE) -> Medium Risk | F9: Risk | G9: 0.5790766 | H9: =IF(E:E=" Low Risk","APPROVE", IF(E:E=" Medium Risk","REVIEW","REJECT")) -> REVIEW | I9: =IF(Table9[[#This Row],[DECISION]]="Approve",3,IF(Table9[[#This Row],[DECISION]]="Review",2,1)) -> 2
A10: CUS00003 | B10: business | C10: 342300 | D10: 116000 | E10: =VLOOKUP(A10,'CREDIT RISK SCORECARD'!A:H,8, FALSE) -> Medium Risk | F10: Risk | G10: 0.67087302 | H10: =IF(E:E=" Low Risk","APPROVE", IF(E:E=" Medium Risk","REVIEW","REJECT")) -> REVIEW | I10: =IF(Table9[[#This Row],[DECISION]]="Approve",3,IF(Table9[[#This Row],[DECISION]]="Review",2,1)) -> 2
A11: CUS00004 | B11: business | C11: 188100 | D11: 59000 | E11: =VLOOKUP(A11,'CREDIT RISK SCORECARD'!A:H,8, FALSE) -> Medium Risk | F11: Risk | G11: 0.66561917 | H11: =IF(E:E=" Low Risk","APPROVE", IF(E:E=" Medium Risk","REVIEW","REJECT")) -> REVIEW | I11: =IF(Table9[[#This Row],[DECISION]]="Approve",3,IF(Table9[[#This Row],[DECISION]]="Review",2,1)) -> 2
A12: CUS00005 | B12: salary | C12: 134300 | D12: 30000 | E12: =VLOOKUP(A12,'CREDIT RISK SCORECARD'!A:H,8, FALSE) -> Low Risk | F12: Safe | G12: 0.37718102 | H12: =IF(E:E=" Low Risk","APPROVE", IF(E:E=" Medium Risk","REVIEW","REJECT")) -> APPROVE | I12: =IF(Table9[[#This Row],[DECISION]]="Approve",3,IF(Table9[[#This Row],[DECISION]]="Review",2,1)) -> 3
A13: CUS00006 | B13: salary | C13: 201700 | D13: 49000 | E13: =VLOOKUP(A13,'CREDIT RISK SCORECARD'!A:H,8, FALSE) -> Low Risk | F13: Safe | G13: 0.35239446 | H13: =IF(E:E=" Low Risk","APPROVE", IF(E:E=" Medium Risk","REVIEW","REJECT")) -> APPROVE | I13: =IF(Table9[[#This Row],[DECISION]]="Approve",3,IF(Table9[[#This Row],[DECISION]]="Review",2,1)) -> 3
A14: CUS00007 | B14: salary | C14: 233900 | D14: 54000 | E14: =VLOOKUP(A14,'CREDIT RISK SCORECARD'!A:H,8, FALSE) -> Low Risk | F14: Safe | G14: 0.36911975 | H14: =IF(E:E=" Low Risk","APPROVE", IF(E:E=" Medium Risk","REVIEW","REJECT")) -> APPROVE | I14: =IF(Table9[[#This Row],[DECISION]]="Approve",3,IF(Table9[[#This Row],[DECISION]]="Review",2,1)) -> 3
A15: CUS00008 | B15: mixed | C15: 124300 | D15: 30000 | E15: =VLOOKUP(A15,'CREDIT RISK SCORECARD'!A:H,8, FALSE) -> Medium Risk | F15: Risk | G15: 0.50772662 | H15: =IF(E:E=" Low Risk","APPROVE", IF(E:E=" Medium Risk","REVIEW","REJECT")) -> REVIEW | I15: =IF(Table9[[#This Row],[DECISION]]="Approve",3,IF(Table9[[#This Row],[DECISION]]="Review",2,1)) -> 2
A16: CUS00009 | B16: business | C16: 313100 | D16: 75000 | E16: =VLOOKUP(A16,'CREDIT RISK SCORECARD'!A:H,8, FALSE) -> Medium Risk | F16: Risk | G16: 0.6310887 | H16: =IF(E:E=" Low Risk","APPROVE", IF(E:E=" Medium Risk","REVIEW","REJECT")) -> REVIEW | I16: =IF(Table9[[#This Row],[DECISION]]="Approve",3,IF(Table9[[#This Row],[DECISION]]="Review",2,1)) -> 2
A17: CUS00010 | B17: business | C17: 352000 | D17: 80000 | E17: =VLOOKUP(A17,'CREDIT RISK SCORECARD'!A:H,8, FALSE) -> Medium Risk | F17: Risk | G17: 0.67125919 | H17: =IF(E:E=" Low Risk","APPROVE", IF(E:E=" Medium Risk","REVIEW","REJECT")) -> REVIEW | I17: =IF(Table9[[#This Row],[DECISION]]="Approve",3,IF(Table9[[#This Row],[DECISION]]="Review",2,1)) -> 2
A18: CUS00011 | B18: salary | C18: 218900 | D18: 52000 | E18: =VLOOKUP(A18,'CREDIT RISK SCORECARD'!A:H,8, FALSE) -> Low Risk | F18: Safe | G18: 0.34081527 | H18: =IF(E:E=" Low Risk","APPROVE", IF(E:E=" Medium Risk","REVIEW","REJECT")) -> APPROVE | I18: =IF(Table9[[#This Row],[DECISION]]="Approve",3,IF(Table9[[#This Row],[DECISION]]="Review",2,1)) -> 3
A19: CUS00012 | B19: mixed | C19: 193400 | D19: 67000 | E19: =VLOOKUP(A19,'CREDIT RISK SCORECARD'!A:H,8, FALSE) -> Medium Risk | F19: Safe | G19: 0.49576141 | H19: =IF(E:E=" Low Risk","APPROVE", IF(E:E=" Medium Risk","REVIEW","REJECT")) -> REVIEW | I19: =IF(Table9[[#This Row],[DECISION]]="Approve",3,IF(Table9[[#This Row],[DECISION]]="Review",2,1)) -> 2
... A2007: CUS02000 | B2007: salary | C2007: 180200 | D2007: 62000 | E2007: =VLOOKUP(A2007,'CREDIT RISK SCORECARD'!A:H,8, FALSE) -> Medium Risk | F2007: Safe | G2007: 0.45084284 | H2007: =IF(E:E=" Low Risk","APPROVE", IF(E:E=" Medium Risk","REVIEW","REJECT")) -> REVIEW | I2007: =IF(Table9[[#This Row],[DECISION]]="Approve",3,IF(Table9[[#This Row],[DECISION]]="Review",2,1)) -> 2
A2008: Total | H2008: =SUBTOTAL(103,Table9[DECISION]) -> 2000
